falcetto/__init__.py
falcetto-1.1.0.dist-info/WHEEL
falcetto-1.1.0.dist-info/METADATA
falcetto-1.1.0.dist-info/RECORD
